otherstuf/__init__.py
otherstuf/chainstuf.py
otherstuf/counterstuf.py
otherstuf/okstuf.py
otherstuf/version.py
otherstuf-1.1.0.dist-info/DESCRIPTION.rst
otherstuf-1.1.0.dist-info/METADATA
otherstuf-1.1.0.dist-info/metadata.json
otherstuf-1.1.0.dist-info/RECORD
otherstuf-1.1.0.dist-info/top_level.txt
otherstuf-1.1.0.dist-info/WHEEL
